joinads/__init__.py
joinads/cli.py
joinads/core.py
joinads/repository.py
joinads/repository_protocol.py
joinads/SQL/__init__.py
joinads/SQL/config.py
joinads/SQL/connection.py
joinads/SQL/query.py
joinads-0.3.1.dist-info/METADATA
joinads-0.3.1.dist-info/WHEEL
joinads-0.3.1.dist-info/entry_points.txt
joinads-0.3.1.dist-info/top_level.txt
joinads-0.3.1.dist-info/RECORD
