Metadata-Version: 2.4
Name: joinads
Version: 0.3.1
Requires-Dist: python-dotenv
Requires-Dist: requests
Requires-Dist: fastapi
Requires-Dist: dbutils
Requires-Dist: pytz
Requires-Dist: pymysql
Requires-Dist: rich
Requires-Dist: typer
Requires-Dist: uvicorn
